speclite/__init__.py
speclite/_astropy_init.py
speclite/accumulate.py
speclite/benchmark.py
speclite/conftest.py
speclite/downsample.py
speclite/filters.py
speclite/redshift.py
speclite/resample.py
speclite/version.py
speclite/data/README.rst
speclite/data/filters/BASS-g.ecsv
speclite/data/filters/BASS-r.ecsv
speclite/data/filters/Euclid-H.ecsv
speclite/data/filters/Euclid-J.ecsv
speclite/data/filters/Euclid-VIS.ecsv
speclite/data/filters/Euclid-Y.ecsv
speclite/data/filters/MzLS-z.ecsv
speclite/data/filters/bessell-B.ecsv
speclite/data/filters/bessell-I.ecsv
speclite/data/filters/bessell-R.ecsv
speclite/data/filters/bessell-U.ecsv
speclite/data/filters/bessell-V.ecsv
speclite/data/filters/cfht_megacam-g.ecsv
speclite/data/filters/cfht_megacam-i.ecsv
speclite/data/filters/cfht_megacam-r.ecsv
speclite/data/filters/cfht_megacam-u.ecsv
speclite/data/filters/cfht_megacam-ustar.ecsv
speclite/data/filters/cfht_megacam-z.ecsv
speclite/data/filters/decam2014-Y.ecsv
speclite/data/filters/decam2014-g.ecsv
speclite/data/filters/decam2014-i.ecsv
speclite/data/filters/decam2014-r.ecsv
speclite/data/filters/decam2014-u.ecsv
speclite/data/filters/decam2014-z.ecsv
speclite/data/filters/decamDR1-Y.ecsv
speclite/data/filters/decamDR1-g.ecsv
speclite/data/filters/decamDR1-i.ecsv
speclite/data/filters/decamDR1-r.ecsv
speclite/data/filters/decamDR1-z.ecsv
speclite/data/filters/decamDR1noatm-Y.ecsv
speclite/data/filters/decamDR1noatm-g.ecsv
speclite/data/filters/decamDR1noatm-i.ecsv
speclite/data/filters/decamDR1noatm-r.ecsv
speclite/data/filters/decamDR1noatm-z.ecsv
speclite/data/filters/gaiadr2-BP.ecsv
speclite/data/filters/gaiadr2-G.ecsv
speclite/data/filters/gaiadr2-RP.ecsv
speclite/data/filters/gaiadr3-BP.ecsv
speclite/data/filters/gaiadr3-G.ecsv
speclite/data/filters/gaiadr3-RP.ecsv
speclite/data/filters/galex-fuv.ecsv
speclite/data/filters/galex-nuv.ecsv
speclite/data/filters/hsc2017-g.ecsv
speclite/data/filters/hsc2017-i.ecsv
speclite/data/filters/hsc2017-i2.ecsv
speclite-0.20.dist-info/METADATA
speclite-0.20.dist-info/WHEEL
speclite-0.20.dist-info/entry_points.txt
speclite-0.20.dist-info/top_level.txt
speclite-0.20.dist-info/RECORD
